[
    {
        "Tournament_Id": "522",
        "Player1 ID": "AZ12345",
        "Player1 Score": 1,
        "Player2 ID": "RT44444",
        "Player2 Score": 0,
        "Round_Number": 1,
        "start_time": "2023-10-13 17:33:18",
        "end_time": "2023-10-13 17:33:20"
    },
    {
        "Tournament_Id": "522",
        "Player1 ID": "QR45632",
        "Player1 Score": 1,
        "Player2 ID": "TY66666",
        "Player2 Score": 0,
        "Round_Number": 1,
        "start_time": "2023-10-13 17:33:20",
        "end_time": "2023-10-13 17:33:21"
    },
    {
        "Tournament_Id": "522",
        "Player1 ID": "AZ12345",
        "Player1 Score": 2,
        "Player2 ID": "QR45632",
        "Player2 Score": 1,
        "Round_Number": 2,
        "start_time": "2023-10-13 17:33:21",
        "end_time": "2023-10-13 17:33:34"
    },
    {
        "Tournament_Id": "522",
        "Player1 ID": "RT44444",
        "Player1 Score": 1,
        "Player2 ID": "TY66666",
        "Player2 Score": 0,
        "Round_Number": 2,
        "start_time": "2023-10-13 17:33:34",
        "end_time": "2023-10-13 17:33:36"
    },
    {
        "Tournament_Id": "522",
        "Player1 ID": "AZ12345",
        "Player1 Score": 3,
        "Player2 ID": "RT44444",
        "Player2 Score": 1,
        "Round_Number": 3,
        "start_time": "2023-10-13 17:33:36",
        "end_time": "2023-10-13 17:33:41"
    },
    {
        "Tournament_Id": "522",
        "Player1 ID": "QR45632",
        "Player1 Score": 2,
        "Player2 ID": "TY66666",
        "Player2 Score": 0,
        "Round_Number": 3,
        "start_time": "2023-10-13 17:33:41",
        "end_time": "2023-10-13 17:33:42"
    },
    {
        "Tournament_Id": "500",
        "Player1 ID": "RT44444",
        "Player1 Score": 1,
        "Player2 ID": "TY66666",
        "Player2 Score": 0,
        "Round_Number": 1,
        "start_time": "2023-10-13 17:38:30",
        "end_time": "2023-10-13 17:38:32"
    },
    {
        "Tournament_Id": "500",
        "Player1 ID": "AZ12345",
        "Player1 Score": 1,
        "Player2 ID": "QR45632",
        "Player2 Score": 0,
        "Round_Number": 1,
        "start_time": "2023-10-13 17:38:32",
        "end_time": "2023-10-13 17:38:34"
    },
    {
        "Tournament_Id": "500",
        "Player1 ID": "RT44444",
        "Player1 Score": 2,
        "Player2 ID": "AZ12345",
        "Player2 Score": 1,
        "Round_Number": 2,
        "start_time": "2023-10-13 17:38:34",
        "end_time": "2023-10-13 17:38:36"
    },
    {
        "Tournament_Id": "500",
        "Player1 ID": "TY66666",
        "Player1 Score": 1,
        "Player2 ID": "QR45632",
        "Player2 Score": 0,
        "Round_Number": 2,
        "start_time": "2023-10-13 17:38:36",
        "end_time": "2023-10-13 17:38:38"
    },
    {
        "Tournament_Id": "500",
        "Player1 ID": "RT44444",
        "Player1 Score": 3,
        "Player2 ID": "TY66666",
        "Player2 Score": 1,
        "Round_Number": 3,
        "start_time": "2023-10-13 17:38:38",
        "end_time": "2023-10-13 17:38:40"
    },
    {
        "Tournament_Id": "500",
        "Player1 ID": "AZ12345",
        "Player1 Score": 2,
        "Player2 ID": "QR45632",
        "Player2 Score": 0,
        "Round_Number": 3,
        "start_time": "2023-10-13 17:38:40",
        "end_time": "2023-10-13 17:38:41"
    },
    {
        "Tournament_Id": "500",
        "Player1 ID": "RT44444",
        "Player1 Score": 4,
        "Player2 ID": "AZ12345",
        "Player2 Score": 2,
        "Round_Number": 4,
        "start_time": "2023-10-13 17:38:41",
        "end_time": "2023-10-13 17:38:43"
    },
    {
        "Tournament_Id": "500",
        "Player1 ID": "TY66666",
        "Player1 Score": 2,
        "Player2 ID": "QR45632",
        "Player2 Score": 0,
        "Round_Number": 4,
        "start_time": "2023-10-13 17:38:43",
        "end_time": "2023-10-13 17:38:44"
    }
]